daily_tasks/__init__.py
daily_tasks/commands/__init__.py
daily_tasks/commands/filter_commands.py
daily_tasks/commands/info_commands.py
daily_tasks/commands/main.py
daily_tasks/commands/main_commands.py
daily_tasks/commands/modification_commands.py
daily_tasks/commands/removal_commands.py
daily_tasks/commands/utilities.py
daily_tasks/data_files/tasks.json
daily_tasks/tests/__init__.py
daily_tasks/tests/test_main_commands.py
daily_tasks/tests/test_sub_commands.py
dailytasks-2.2.0.dist-info/LICENSE
dailytasks-2.2.0.dist-info/METADATA
dailytasks-2.2.0.dist-info/WHEEL
dailytasks-2.2.0.dist-info/entry_points.txt
dailytasks-2.2.0.dist-info/top_level.txt
dailytasks-2.2.0.dist-info/RECORD
