Metadata-Version: 2.1
Name: dailytasks
Version: 2.2.0
Summary: A tasks manager for those who like work from shell.
Author-email: LuisanaMTDev <luisanamartineztorres25@gmail.com>
License: Apache License
Classifier: Environment :: Console
Classifier: Intended Audience :: Developers
Classifier: License :: OSI Approved :: Apache Software License
Classifier: Programming Language :: Python :: 3.11
Classifier: Topic :: Utilities
Requires-Python: >=3.11
License-File: LICENSE
Requires-Dist: click >=8.1.7
Requires-Dist: colorama >=0.4.6
